claude_log_viewer/__init__.py
claude_log_viewer/activities_to_buckets.py
claude_log_viewer/api_poller.py
claude_log_viewer/app.py
claude_log_viewer/backfill.py
claude_log_viewer/cli_tools.py
claude_log_viewer/database.py
claude_log_viewer/git_discovery.py
claude_log_viewer/git_manager.py
claude_log_viewer/snapshot_pipeline.py
claude_log_viewer/timeline_builder.py
claude_log_viewer/token_counter.py
claude_log_viewer/token_utils.py
claude_log_viewer/static/css/base.css
claude_log_viewer/static/css/drawer.css
claude_log_viewer/static/css/header.css
claude_log_viewer/static/css/main.css
claude_log_viewer/static/css/modal.css
claude_log_viewer/static/css/session-cards.css
claude_log_viewer/static/css/table.css
claude_log_viewer/static/css/timeline.css
claude_log_viewer/static/css/usage.css
claude_log_viewer/static/js/api.js
claude_log_viewer/static/js/config.js
claude_log_viewer/static/js/entries.js
claude_log_viewer/static/js/events.js
claude_log_viewer/static/js/main.js
claude_log_viewer/static/js/modals.js
claude_log_viewer/static/js/sessions.js
claude_log_viewer/static/js/settings.js
claude_log_viewer/static/js/state.js
claude_log_viewer/static/js/timeline.js
claude_log_viewer/static/js/usage.js
claude_log_viewer/static/js/utils.js
claude_log_viewer/templates/index.html
claude_log_viewer-1.0.2.dist-info/licenses/LICENSE
claude_log_viewer-1.0.2.dist-info/METADATA
claude_log_viewer-1.0.2.dist-info/WHEEL
claude_log_viewer-1.0.2.dist-info/entry_points.txt
claude_log_viewer-1.0.2.dist-info/top_level.txt
claude_log_viewer-1.0.2.dist-info/RECORD
