Metadata-Version: 2.4
Name: claude-log-viewer
Version: 1.0.2
Summary: An interactive web-based viewer for Claude Code JSONL transcript files
Author: Indate
License: MIT
Project-URL: Homepage, https://github.com/indate/claude-log-viewer
Project-URL: Repository, https://github.com/indate/claude-log-viewer
Project-URL: Issues, https://github.com/indate/claude-log-viewer/issues
Keywords: claude,claude-code,logging,viewer,transcript,jsonl,debugging
Classifier: Development Status :: 4 - Beta
Classifier: Intended Audience :: Developers
Classifier: Topic :: Software Development :: Debuggers
Classifier: License :: OSI Approved :: MIT License
Classifier: Programming Language :: Python :: 3
Classifier: Programming Language :: Python :: 3.9
Classifier: Programming Language :: Python :: 3.10
Classifier: Programming Language :: Python :: 3.11
Classifier: Programming Language :: Python :: 3.12
Classifier: Framework :: Flask
Requires-Python: >=3.9
License-File: LICENSE
Requires-Dist: flask>=3.0.0
Requires-Dist: watchdog>=3.0.0
Requires-Dist: requests>=2.31.0
Requires-Dist: tiktoken>=0.12.0
Dynamic: license-file
